swatch/__init__.py
swatch/slurm_watch.py
swatch_slurm-0.1.1.dist-info/METADATA
swatch_slurm-0.1.1.dist-info/WHEEL
swatch_slurm-0.1.1.dist-info/entry_points.txt
swatch_slurm-0.1.1.dist-info/licenses/LICENSE
swatch_slurm-0.1.1.dist-info/RECORD
