Metadata-Version: 2.4
Name: swatch-slurm
Version: 0.1.1
Summary: A sleek, modern job monitoring tool for Slurm workload manager
Project-URL: Homepage, https://github.com/Jakeelamb/SWATCH
Project-URL: Bug Tracker, https://github.com/Jakeelamb/SWATCH/issues
Author-email: Jake Lamb <jakelamb74@gmail.com>
License: MIT License
License-File: LICENSE
Classifier: License :: OSI Approved :: MIT License
Classifier: Operating System :: OS Independent
Classifier: Programming Language :: Python :: 3
Classifier: Topic :: System :: Monitoring
Classifier: Topic :: System :: Systems Administration
Requires-Python: >=3.7
Requires-Dist: paramiko
Requires-Dist: pillow
Requires-Dist: pyqt5
Provides-Extra: dev
Requires-Dist: black>=22.0; extra == 'dev'
Requires-Dist: flake8>=4.0; extra == 'dev'
Requires-Dist: isort>=5.0; extra == 'dev'
Requires-Dist: mypy>=1.0; extra == 'dev'
Requires-Dist: pytest>=7.0; extra == 'dev'
Provides-Extra: docs
Requires-Dist: sphinx-rtd-theme>=1.0; extra == 'docs'
Requires-Dist: sphinx>=4.0; extra == 'docs'
